sonyflake/__init__.py
sonyflake/py.typed
sonyflake/sonyflake.py
sonyflake-2.0.2.dist-info/METADATA
sonyflake-2.0.2.dist-info/WHEEL
sonyflake-2.0.2.dist-info/RECORD
