Metadata-Version: 2.4
Name: sonyflake
Version: 2.0.2
Summary: A distributed unique ID generator inspired by Twitter's Snowflake
Project-URL: Homepage, https://github.com/iyad-f/sonyflake
Project-URL: Issues, https://github.com/iyad-f/sonyflake/issues
Project-URL: Repository, https://github.com/iyad-f/sonyflake
Author: Iyad
License-Expression: Apache-2.0
Keywords: snowflake,snowflake py,snowflake.py,sonyflake,sonyflake py
Classifier: Development Status :: 5 - Production/Stable
Classifier: Intended Audience :: Developers
Classifier: Natural Language :: English
Classifier: Operating System :: OS Independent
Classifier: Programming Language :: Python :: 3 :: Only
Classifier: Programming Language :: Python :: 3.10
Classifier: Programming Language :: Python :: 3.11
Classifier: Programming Language :: Python :: 3.12
Classifier: Programming Language :: Python :: 3.13
Classifier: Topic :: Internet
Classifier: Topic :: Software Development :: Libraries
Classifier: Topic :: Software Development :: Libraries :: Python Modules
Classifier: Topic :: System :: Distributed Computing
Classifier: Typing :: Typed
Requires-Python: >=3.11
